netra_adapter/__init__.py
netra_adapter/adapter.py
netra_adapter/utils.py
netra_adapter-0.1.5.dist-info/LICENSE
netra_adapter-0.1.5.dist-info/METADATA
netra_adapter-0.1.5.dist-info/WHEEL
netra_adapter-0.1.5.dist-info/top_level.txt
netra_adapter-0.1.5.dist-info/RECORD
